controlpool/__init__.py
controlpool/_messages.py
controlpool-0.4.0.dist-info/LICENSE
controlpool-0.4.0.dist-info/METADATA
controlpool-0.4.0.dist-info/WHEEL
controlpool-0.4.0.dist-info/top_level.txt
controlpool-0.4.0.dist-info/RECORD
