Metadata-Version: 2.2
Name: controlpool
Version: 0.4.0
Summary: Multiprocessing controllable pool
Author-email: Alexander Ershov <fiaf1@mail.ru>
Project-URL: Homepage, https://gitlab.com/Baumgarthner/controlpool
Project-URL: Bug Tracker, https://gitlab.com/Baumgarthner/controlpool/-/issues
Classifier: Development Status :: 4 - Beta 
Classifier: Programming Language :: Python :: 3
Classifier: License :: OSI Approved :: GNU General Public License v3 (GPLv3)
Classifier: Operating System :: POSIX
Classifier: Operating System :: Unix
Classifier: Intended Audience :: Developers
Classifier: Intended Audience :: Science/Research
Classifier: Topic :: System :: Distributed Computing
Requires-Python: >=3.7
License-File: LICENSE
